README.md
codebuild_ci/__init__.py
codebuild_ci/__main__.py
codebuild_ci/clients.py
codebuild_ci/codebuild.py
codebuild_ci/logs.py
codebuild_ci/waiter.py
codebuild_ci/waiter_model.py
codebuild_ci-0.2.0.dist-info/METADATA
codebuild_ci-0.2.0.dist-info/WHEEL
codebuild_ci-0.2.0.dist-info/entry_points.txt
codebuild_ci-0.2.0.dist-info/RECORD
