Metadata-Version: 2.1
Name: codebuild-ci
Version: 0.2.0
Summary: Command line utility to trigger and wait for Code build Pipeline to complete
Home-page: https://github.com/satyamsoni2211/codebuild_ci
License: MIT
Keywords: python,aws,codebuild,ci,devops,cli
Author: satyam soni
Requires-Python: >=3.9
Classifier: Development Status :: 4 - Beta
Classifier: Framework :: AWS CDK
Classifier: License :: OSI Approved :: MIT License
Classifier: Operating System :: OS Independent
Classifier: Programming Language :: Python :: 3
Classifier: Programming Language :: Python :: 3.9
Classifier: Programming Language :: Python :: 3.10
Classifier: Programming Language :: Python :: 3.11
Classifier: Programming Language :: Python :: 3.10
Classifier: Programming Language :: Python :: 3.11
Classifier: Programming Language :: Python :: 3.9
Classifier: Programming Language :: Python :: Implementation
Requires-Dist: boto3 (>=1.26.116,<2.0.0)
Requires-Dist: typer[all] (>=0.7.0,<0.8.0)
Project-URL: Repository, https://github.com/satyamsoni2211/codebuild_ci
